{
  "ro": {
    "全部": 0,
    "全職": 1,
    "兼職": 2,
    "高階": 3,
    "派遣": 4
  },
  "area": {
    "台北市": 6001001000,
    "新北市": 6001002000,
    "宜蘭縣": 6001003000,
    "基隆市": 6001004000,
    "桃園市": 6001005000,
    "新竹縣市": 6001006000,
    "苗栗縣": 6001007000,
    "台中市": 6001008000,
    "彰化縣": 6001010000,
    "南投縣": 6001011000,
    "雲林縣": 6001012000,
    "嘉義縣市": 6001013000,
    "台南市": 6001014000,
    "高雄市": 6001016000,
    "屏東縣": 6001018000,
    "台東縣": 6001019000,
    "花蓮縣": 6001020000,
    "澎湖縣": 6001021000,
    "金門縣": 6001022000,
    "連江縣": 6001023000
  },
  "isnew": {
    "本日最新": 0,
    "三日內": 3,
    "一週內": 7,
    "兩週內": 14,
    "一個月內": 30
  },
  "jobexp": {
    "1年以下": 1,
    "1-3年": 3,
    "3-5年": 5,
    "5-10年": 10,
    "10年以上": 99
  },
  "mode": {
    "摘要": "s",
    "列表": "l"
  },
  "order": {
    "符合度排序": 14,
    "日期排序": 16,
    "學歷": 4,
    "經歷": 3,
    "應徵人數": 7,
    "待遇": 13
  },
  "asc": {
    "遞減": 0,
    "遞增": 1
  }
}
